[{
  "type": "wig",
  "name": "ALE-raw-depth",
  "format": "bedgraph",
  "url": "{{ page.ale_wig_base }}",
  "indexURL": "{{ page.ale_wig_base }}.tbi",
  "color": "red",
  "guideLines": [
    {"color": "green", "dotted": true, "y": 0}
  ],
  "graphType": "line",
  "windowFunction": "mean",
  "pointSize": 3,
  "autoscale": true
},
{
  "type": "wig",
  "name": "ALE-depth",
  "format": "bedgraph",
  "url": "{{ page.ale_wig_depth }}",
  "indexURL": "{{ page.ale_wig_depth }}.tbi",
  "color": "red",
  "guideLines": [
    {"color": "green", "dotted": true, "y": 0}
  ],
  "graphType": "line",
  "windowFunction": "mean",
  "pointSize": 3,
  "autoscale": true
},
{
  "type": "wig",
  "name": "ALE-insert",
  "format": "bedgraph",
  "url": "{{ page.ale_wig_insert }}",
  "indexURL": "{{ page.ale_wig_insert }}.tbi",
  "color": "red",
  "guideLines": [
    {"color": "green", "dotted": true, "y": 0}
  ],
  "graphType": "line",
  "windowFunction": "mean",
  "pointSize": 3,
  "autoscale": true
},
{
  "type": "wig",
  "name": "ALE-kmer",
  "format": "bedgraph",
  "url": "{{ page.ale_wig_kmer }}",
  "indexURL": "{{ page.ale_wig_kmer }}.tbi",
  "color": "red",
  "guideLines": [
    {"color": "green", "dotted": true, "y": 0}
  ],
  "graphType": "line",
  "windowFunction": "mean",
  "pointSize": 3,
  "autoscale": true
},
{
  "type": "wig",
  "name": "ALE-place",
  "format": "bedgraph",
  "url": "{{ page.ale_wig_place }}",
  "indexURL": "{{ page.ale_wig_place }}.tbi",
  "color": "red",
  "guideLines": [
    {"color": "green", "dotted": true, "y": 0}
  ],
  "graphType": "line",
  "windowFunction": "mean",
  "pointSize": 3,
  "autoscale": true
},
{
  "type": "wig",
  "name": "REAPR",
  "format": "bedgraph",
  "url": "{{ page.reapr_score_per_base }}",
  "indexURL": "{{ page.reapr_score_per_base }}.tbi",
  "color": "red",
  "guideLines": [
    {"color": "green", "dotted": true, "y": 0}
  ],
  "graphType": "line",
  "windowFunction": "mean",
  "pointSize": 3,
  "autoscale": false,
  "min": 0,
  "max": 1
},
{
  "type": "wig",
  "name": "CRAQ-AQI",
  "format": "bedgraph",
  "url": "{{ page.craq_aqi_bedgraph }}",
  "indexURL": "{{ page.craq_aqi_bedgraph }}.tbi",
  "color": "red",
  "guideLines": [
    {"color": "green", "dotted": true, "y": 0}
  ],
  "graphType": "line",
  "windowFunction": "mean",
  "pointSize": 3,
  "autoscale": false,
  "min": 0,
  "max": 100
},
{
  "type": "alignment",
  "format": "bam",  
  "name": "Alignments",
  "url": "{{ page.reapr_bam }}",
  "indexURL": "{{ page.reapr_bai }}"
}
]